
<annotation>
    <folder>images</folder>
    <filename>Faces4.png</filename>
    <size>
        <width>450</width>
        <height>296</height>
        <depth>3</depth>
    </size>
    <segmented>0</segmented>
    <object>
        <name>Face</name>
        <pose>Unspecified</pose>
        <truncated>0</truncated>
        <occluded>0</occluded>
        <difficult>0</difficult>
        <bndbox>
            <xmin>77</xmin>
            <ymin>32</ymin>
            <xmax>150</xmax>
            <ymax>127</ymax>
        </bndbox>
    </object>
    <object>
        <name>Face</name>
        <pose>Unspecified</pose>
        <truncated>0</truncated>
        <occluded>0</occluded>
        <difficult>0</difficult>
        <bndbox>
            <xmin>191</xmin>
            <ymin>34</ymin>
            <xmax>260</xmax>
            <ymax>113</ymax>
        </bndbox>
    </object>
    <object>
        <name>Face</name>
        <pose>Unspecified</pose>
        <truncated>0</truncated>
        <occluded>0</occluded>
        <difficult>0</difficult>
        <bndbox>
            <xmin>300</xmin>
            <ymin>35</ymin>
            <xmax>373</xmax>
            <ymax>111</ymax>
        </bndbox>
    </object>
    <object>
        <name>Face</name>
        <pose>Unspecified</pose>
        <truncated>0</truncated>
        <occluded>0</occluded>
        <difficult>0</difficult>
        <bndbox>
            <xmin>359</xmin>
            <ymin>175</ymin>
            <xmax>429</xmax>
            <ymax>251</ymax>
        </bndbox>
    </object>
    <object>
        <name>Face</name>
        <pose>Unspecified</pose>
        <truncated>0</truncated>
        <occluded>0</occluded>
        <difficult>0</difficult>
        <bndbox>
            <xmin>244</xmin>
            <ymin>186</ymin>
            <xmax>315</xmax>
            <ymax>259</ymax>
        </bndbox>
    </object>
    <object>
        <name>Face</name>
        <pose>Unspecified</pose>
        <truncated>0</truncated>
        <occluded>0</occluded>
        <difficult>0</difficult>
        <bndbox>
            <xmin>123</xmin>
            <ymin>173</ymin>
            <xmax>207</xmax>
            <ymax>251</ymax>
        </bndbox>
    </object>
    <object>
        <name>Face</name>
        <pose>Unspecified</pose>
        <truncated>0</truncated>
        <occluded>0</occluded>
        <difficult>0</difficult>
        <bndbox>
            <xmin>15</xmin>
            <ymin>176</ymin>
            <xmax>90</xmax>
            <ymax>254</ymax>
        </bndbox>
    </object>
</annotation>